fake_https_server/__init__.py
fake_https_server/request.py
fake_https_server/server.py
fake_https_server-0.0.10.dist-info/licenses/LICENSE.txt
fake_https_server-0.0.10.dist-info/METADATA
fake_https_server-0.0.10.dist-info/WHEEL
fake_https_server-0.0.10.dist-info/top_level.txt
fake_https_server-0.0.10.dist-info/RECORD
