Metadata-Version: 2.4
Name: fake-https-server
Version: 0.0.10
Summary: Fake http and https servers
Author-email: Fabrício Barros Cabral <fabriciofx@gmail.com>
License-Expression: MIT
Project-URL: homepage, https://github.com/fabriciofx/fake-https-server
Project-URL: bug-tracker, https://github.com/fabriciofx/fake-https-server/issues
Keywords: fake,mock,http,https,server,request
Requires-Python: >=3.14
License-File: LICENSE.txt
Requires-Dist: random-port>=0.0.5
Dynamic: license-file
